ins_hamming.v


module hamming(oOut,
	iA, iB
	);
	
	output	[31:0]	oOut;
	
	input	[31:0]	iA, iB;
	
	wire	[31:0]	wC;
	
	assign oOut = ((((wC[0]+wC[1])+(wC[2]+wC[3]))+((wC[4]+wC[5])+(wC[6]+wC[7])))+
		(((wC[8]+wC[9])+(wC[10]+wC[11]))+((wC[12]+wC[13])+(wC[14]+wC[15]))))+
		((((wC[16]+wC[17])+(wC[18]+wC[19]))+((wC[20]+wC[21])+(wC[22]+wC[23])))+
		(((wC[24]+wC[25])+(wC[26]+wC[27]))+((wC[28]+wC[29])+(wC[30]+wC[31]))));
	assign wC = iA ^ iB;
	
endmodule
	
module hammingPlus(oRes,
	iA, iB,
	iOp,
	iClk, iClk_en,
	iReset);

	output	[31:0]	oRes;
	
	input	[31:0]	iA, iB;
	input	iOp;
	
	input	iClk, iReset, iClk_en;
	
	reg	[31:0]	rAcc, rCnt, rRes;
	reg	rDone;
	
	wire	[31:0]	wH;
	
	assign	oRes = rRes;
	
	hamming	comp0(wH, iA, iB);
	
	always@(posedge iClk or posedge iReset or negedge iClk_en) begin
		if (iReset) begin
			rRes <= 32'h0;
			rDone <= 0;
		end else if (!iClk_en) rDone <= 0;
		else begin
			rDone <= 1;
			if (!rDone) begin
				if (!iOp) begin // clear and report result
					rRes <= rAcc;
				end
			end
		end
	end
	
	always@(negedge iClk or posedge iReset) begin
		if (iReset) begin
			rAcc <= 32'h0;
			rCnt <= 32'h0;
		end else if (iClk_en && rDone) begin
			if (!iOp) begin
				rAcc <= 32'h0;
				rCnt <= 32'h0;
			end else begin
				rAcc <= rAcc + wH;
				rCnt <= rCnt + 32'h1;
			end
		end
	end

endmodule

	
module hammingAvg4(oRes,
	iA, iB,
	iOp,
	iClk, iClk_en,
	iReset);

	output	[31:0]	oRes;
	
	input	[31:0]	iA, iB;
	input	iOp;
	
	input	iClk, iReset, iClk_en;
	
	reg	[31:0]	rAcc, rCnt, rRes;
	reg	rDone;
	
	wire	[31:0]	wH;
	
	assign	oRes = rRes;
	
	hamming	comp0(wH, iA, iB);
	
	always@(posedge iClk or posedge iReset or negedge iClk_en) begin
		if (iReset) begin
			rRes <= 32'h0;
			rDone <= 0;
		end else if (!iClk_en) rDone <= 0;
		else begin
			rDone <= 1;
			if (!rDone) begin
				if (!iOp) begin // clear and report result
					rRes <= (rCnt>0)?(rAcc*4 + rCnt/2)/rCnt:0;
				end
			end
		end 
	end
	
	always@(negedge iClk or posedge iReset) begin
		if (iReset) begin
			rAcc <= 32'h0;
			rCnt <= 32'h0;
		end else if (iClk_en && rDone) begin
			if (!iOp) begin
				rAcc <= 32'h0;
				rCnt <= 32'h0;
			end else begin
				rAcc <= rAcc + wH;
				rCnt <= rCnt + 32'h1;
			end
		end
	end

endmodule

ins_hamming_tb.v


module hamming_tb;
	
	wire	[31:0]	a, d;//, b, c, d;
	reg	[31:0]	b, c;
	
	reg	[31:0]	cnt;
	wire	clk;
	reg	clk_en, reset;
	reg	[0:0]	op;
	
	initial cnt <= 0;
	always #1 cnt<=cnt+1;
	assign clk = cnt[0];
	
	initial begin
		reset <= 1;
		#2
		reset <= 0;
	end
	
	initial clk_en <= 0;
	always #4 clk_en <= ~clk_en;
	
	initial begin
		op <= 0;
		#10
		op <= 1;
		#34
		op <= 0;
	end
	
	hammingAvg4 comp0(a, b, c, op, clk, clk_en, reset);
	hamming comp1(d, b, c);
	
// 	assign b = cnt*3+2;
// 	assign c = cnt*5+7;

	initial begin
		b <= 32;c<=1;
		#8
		b <= 32'hf0800000;c<=32'h0a000070;
		#8
		b<= 32'he1000000;c<=32'h85000000;
		#8
		b<=32'hc2800000;c<=32'h19800000;
		#8
		b<=0;c<=0;
	end
	
	
	initial begin
		$dumpfile("out.vcd");
		$dumpvars(0,hamming_tb);
		$monitor(clk);
		
		#100;
		$finish;
	end
	
endmodule

out.vcd
$date
	Fri Apr  1 10:27:06 2016
$end
$version
	Icarus Verilog
$end
$timescale
	1s
$end
$scope module hamming_tb $end
$var wire 32 ! d [31:0] $end
$var wire 1 " clk $end
$var wire 32 # a [31:0] $end
$var reg 32 $ b [31:0] $end
$var reg 32 % c [31:0] $end
$var reg 1 & clk_en $end
$var reg 32 ' cnt [31:0] $end
$var reg 1 ( op $end
$var reg 1 ) reset $end
$scope module comp0 $end
$var wire 32 * iA [31:0] $end
$var wire 32 + iB [31:0] $end
$var wire 1 " iClk $end
$var wire 1 & iClk_en $end
$var wire 1 ( iOp $end
$var wire 1 ) iReset $end
$var wire 32 , oRes [31:0] $end
$var wire 32 - wH [31:0] $end
$var reg 32 . rAcc [31:0] $end
$var reg 32 / rCnt [31:0] $end
$var reg 1 0 rDone $end
$var reg 32 1 rRes [31:0] $end
$scope module comp0 $end
$var wire 32 2 iA [31:0] $end
$var wire 32 3 iB [31:0] $end
$var wire 32 4 wC [31:0] $end
$var wire 32 5 oOut [31:0] $end
$upscope $end
$upscope $end
$scope module comp1 $end
$var wire 32 6 iA [31:0] $end
$var wire 32 7 iB [31:0] $end
$var wire 32 8 wC [31:0] $end
$var wire 32 9 oOut [31:0] $end
$upscope $end
$upscope $end
$enddefinitions $end
#0
$dumpvars
b10 9
b100001 8
b1 7
b100000 6
b10 5
b100001 4
b1 3
b100000 2
b0 1
00
b0 /
b0 .
b10 -
b0 ,
b1 +
b100000 *
1)
0(
b0 '
0&
b1 %
b100000 $
b0 #
0"
b10 !
$end
#1
1"
b1 '
#2
0"
b10 '
0)
#3
1"
b11 '
#4
0"
b100 '
1&
#5
10
1"
b101 '
#6
0"
b110 '
#7
1"
b111 '
#8
00
b1010 -
b1010 5
b1010 !
b1010 9
0"
b11111010100000000000000001110000 4
b11111010100000000000000001110000 8
b1000 '
0&
b1010000000000000000001110000 %
b1010000000000000000001110000 +
b1010000000000000000001110000 3
b1010000000000000000001110000 7
b11110000100000000000000000000000 $
b11110000100000000000000000000000 *
b11110000100000000000000000000000 2
b11110000100000000000000000000000 6
#9
1"
b1001 '
#10
0"
b1010 '
1(
#11
1"
b1011 '
#12
0"
b1100 '
1&
#13
10
1"
b1101 '
#14
b1 /
b1010 .
0"
b1110 '
#15
1"
b1111 '
#16
00
b11 -
b11 5
b11 !
b11 9
0"
b1100100000000000000000000000000 4
b1100100000000000000000000000000 8
b10000 '
0&
b10000101000000000000000000000000 %
b10000101000000000000000000000000 +
b10000101000000000000000000000000 3
b10000101000000000000000000000000 7
b11100001000000000000000000000000 $
b11100001000000000000000000000000 *
b11100001000000000000000000000000 2
b11100001000000000000000000000000 6
#17
1"
b10001 '
#18
0"
b10010 '
#19
1"
b10011 '
#20
0"
b10100 '
1&
#21
10
1"
b10101 '
#22
b10 /
b1101 .
0"
b10110 '
#23
1"
b10111 '
#24
00
b110 -
b110 5
b110 !
b110 9
0"
b11011011000000000000000000000000 4
b11011011000000000000000000000000 8
b11000 '
0&
b11001100000000000000000000000 %
b11001100000000000000000000000 +
b11001100000000000000000000000 3
b11001100000000000000000000000 7
b11000010100000000000000000000000 $
b11000010100000000000000000000000 *
b11000010100000000000000000000000 2
b11000010100000000000000000000000 6
#25
1"
b11001 '
#26
0"
b11010 '
#27
1"
b11011 '
#28
0"
b11100 '
1&
#29
10
1"
b11101 '
#30
b11 /
b10011 .
0"
b11110 '
#31
1"
b11111 '
#32
00
b0 -
b0 5
b0 !
b0 9
0"
b0 4
b0 8
b100000 '
0&
b0 %
b0 +
b0 3
b0 7
b0 $
b0 *
b0 2
b0 6
#33
1"
b100001 '
#34
0"
b100010 '
#35
1"
b100011 '
#36
0"
b100100 '
1&
#37
10
1"
b100101 '
#38
b100 /
0"
b100110 '
#39
1"
b100111 '
#40
00
0"
b101000 '
0&
#41
1"
b101001 '
#42
0"
b101010 '
#43
1"
b101011 '
#44
0"
b101100 '
1&
0(
#45
b10011 #
b10011 ,
b10011 1
10
1"
b101101 '
#46
b0 /
b0 .
0"
b101110 '
#47
1"
b101111 '
#48
00
0"
b110000 '
0&
#49
1"
b110001 '
#50
0"
b110010 '
#51
1"
b110011 '
#52
0"
b110100 '
1&
#53
b0 #
b0 ,
b0 1
10
1"
b110101 '
#54
0"
b110110 '
#55
1"
b110111 '
#56
00
0"
b111000 '
0&
#57
1"
b111001 '
#58
0"
b111010 '
#59
1"
b111011 '
#60
0"
b111100 '
1&
#61
10
1"
b111101 '
#62
0"
b111110 '
#63
1"
b111111 '
#64
00
0"
b1000000 '
0&
#65
1"
b1000001 '
#66
0"
b1000010 '
#67
1"
b1000011 '
#68
0"
b1000100 '
1&
#69
10
1"
b1000101 '
#70
0"
b1000110 '
#71
1"
b1000111 '
#72
00
0"
b1001000 '
0&
#73
1"
b1001001 '
#74
0"
b1001010 '
#75
1"
b1001011 '
#76
0"
b1001100 '
1&
#77
10
1"
b1001101 '
#78
0"
b1001110 '
#79
1"
b1001111 '
#80
00
0"
b1010000 '
0&
#81
1"
b1010001 '
#82
0"
b1010010 '
#83
1"
b1010011 '
#84
0"
b1010100 '
1&
#85
10
1"
b1010101 '
#86
0"
b1010110 '
#87
1"
b1010111 '
#88
00
0"
b1011000 '
0&
#89
1"
b1011001 '
#90
0"
b1011010 '
#91
1"
b1011011 '
#92
0"
b1011100 '
1&
#93
10
1"
b1011101 '
#94
0"
b1011110 '
#95
1"
b1011111 '
#96
00
0"
b1100000 '
0&
#97
1"
b1100001 '
#98
0"
b1100010 '
#99
1"
b1100011 '
#100
0"
b1100100 '
1&
