ins_census.v

module census(oRes,
	iA,
	iOp, iReset,
	iClk, iClk_en);

	output	[31:0]	oRes;
	
	input	[31:0]	iA;
	input	[3:0]	iOp;
	
	input	iClk, iClk_en, iReset;
	
	reg	[31:0]	rRes;
	reg	[967:0]	rMatrix; //8*121-1
	reg	[7:0]	rCmp;
	reg	[119:0]	rCodec0;
	reg	[31:0]	rAcc;

	reg	[31:0]	rCnt;
	reg	rDone;
	
	wire	[119:0]	wCodec, wH;
	wire	[6:0]	wSum;
	
	assign	oRes = rRes;
	assign	wH = rCodec0 ^ wCodec;
	assign	wSum = wH[0]+wH[1]+wH[2]+wH[3]+wH[4]+wH[5]+wH[6]+wH[7]+wH[8]+wH[9]+wH[10]+wH[11]+wH[12]+wH[13]+wH[14]+wH[15]+wH[16]+wH[17]+wH[18]+wH[19]+wH[20]+wH[21]+wH[22]+wH[23]+wH[24]+wH[25]+wH[26]+wH[27]+wH[28]+wH[29]+wH[30]+wH[31]+wH[32]+wH[33]+wH[34]+wH[35]+wH[36]+wH[37]+wH[38]+wH[39]+wH[40]+wH[41]+wH[42]+wH[43]+wH[44]+wH[45]+wH[46]+wH[47]+wH[48]+wH[49]+wH[50]+wH[51]+wH[52]+wH[53]+wH[54]+wH[55]+wH[56]+wH[57]+wH[58]+wH[59]+wH[60]+wH[61]+wH[62]+wH[63]+wH[64]+wH[65]+wH[66]+wH[67]+wH[68]+wH[69]+wH[70]+wH[71]+wH[72]+wH[73]+wH[74]+wH[75]+wH[76]+wH[77]+wH[78]+wH[79]+wH[80]+wH[81]+wH[82]+wH[83]+wH[84]+wH[85]+wH[86]+wH[87]+wH[88]+wH[89]+wH[90]+wH[91]+wH[92]+wH[93]+wH[94]+wH[95]+wH[96]+wH[97]+wH[98]+wH[99]+wH[100]+wH[101]+wH[102]+wH[103]+wH[104]+wH[105]+wH[106]+wH[107]+wH[108]+wH[109]+wH[110]+wH[111]+wH[112]+wH[113]+wH[114]+wH[115]+wH[116]+wH[117]+wH[118]+wH[119];
	
	genvar i;
	
	generate
		for (i=0;i<60;i=i+1) begin: codec_low
			assign wCodec[i] = rMatrix[(i+1)*8-1:i*8]<rCmp;
		end
		for (i=61;i<=120;i=i+1) begin: codec_high
			assign wCodec[i-1] = rMatrix[(i+1)*8-1:i*8]<rCmp;
		end
	endgenerate
	
	always@(posedge iClk or posedge iReset or negedge iClk_en)begin
		if (iReset) begin
			rCnt <= 0;
			rDone <= 0;
		end else if (!iClk_en) rDone <= 0;
		else begin
			rDone <= 1;
			if (!rDone) begin
				rCnt <= rCnt + 1;
				case (iOp)
					4'h1:begin // add n max (n<=6)
// 						rMatrix <= ~((~rMatrix)<<(iA[3:0]*8));
// 						rMatrix <= (rMatrix<<(iA[3:0]*8)) | ({88{1'b1}}>>(88-iA[3:0]*8));
						rMatrix <= (rMatrix<<(iA[2:0]*8)) | ({48{1'b1}}>>(48-iA[2:0]*8));
					end
					4'h2:begin // add 1 data
						rMatrix <= {rMatrix[967-8:0], iA[7:0]};
					end
					4'h3:begin // set counter
						rCnt <= iA;
					end
					
					////////////////////With result///////////////////////////
					4'h7:begin // get counter
					end
					4'h8:begin // compare with iA, get output 31:0
						rCmp <= iA[7:0];
						rCodec0 <= wCodec; // move last to rCodec1
					end
					4'h9:begin // get output 31:0
					end
					4'ha:begin // get output 63:32
					end
					4'hb:begin // get output 95:64
					end
					4'hc:begin // get output 119:96
					end
					4'hd:begin // hamming !;
					end
					4'he:begin // hamming plus!
					end
// 					default:begin// (0):clear
// 						rMatrix <= {968{1'b1}};
// 					end
				endcase
			end
		end
	end
	
	
	always@(negedge iClk or posedge iReset)begin
		if (iReset) begin
			rAcc <= 0;
		end else if (iClk_en && rDone) case (iOp)
			4'h4:begin // set rAcc
				rAcc <= iA;
			end
			4'h8:begin // compare with iA, get output 31:0
// 				rCodec0 <= wCodec; // move this to rCodec0
				rRes <= wCodec[31:0];
			end
		//////////////////////////////////////
			4'he:begin
				rAcc <= rAcc + {24'd0, wSum};
				rRes <= rAcc + {24'd0, wSum};
			end
			4'hd:begin
				rRes <= {24'd0, wSum};
			end
			4'h9:begin // get output 31:0
				rRes <= wCodec[31:0];
			end
			4'ha:begin // get output 63:32
				rRes <= wCodec[63:32];
			end
			4'hb:begin // get output 95:64
				rRes <= wCodec[95:64];
			end
			4'hc:begin // get output 119:96
				rRes <= {8'd0, wCodec[119:96]};
			end
			4'h7:begin // get counter
				rRes <= rCnt;
			end
			default: begin
				rRes <= 0;
			end
		endcase
	end
	
endmodule

ins_census_tb.v


module census_tb;
	
	wire	[31:0]	r;//, b, c, d;
	reg	[31:0]	a, b, c, d;
	
	reg	[31:0]	cnt;
	wire	clk;
	reg	clk_en, reset;
	reg	[3:0]	op;
	
	initial cnt <= 0;
	always #1 cnt<=cnt+1;
	assign clk = cnt[0];
	
	initial begin
		reset <= 1;
		#2
		reset <= 0;
	end
	
	initial clk_en <= 0;
	always #4 clk_en <= ~clk_en;
	
	initial begin
		op <= 4'h0;#10
		op <= 4'h1;#80
		op <= 4'h1;#50
		op <= 4'h2;#30
		op <= 4'h2;#8
		op <= 4'h2;#8
		op <= 4'h1;#8
		op <= 4'h1;#8
		op <= 4'h1;#8
		op <= 4'h1;#8
		op <= 4'h1;#8
		op <= 4'h8;#8
		op <= 4'h8;#8
		op <= 4'hd;#8
		op <= 4'h7;
	end
	
	census comp0(r, a, op, reset, clk, clk_en);
	
// 	assign b = cnt*3+2;
// 	assign c = cnt*5+7;

	initial begin
		#10
		a<=8'h6;
		#80
		#80
		#50
		a<=10;
		#50
		;
	end
	
	initial begin
		#10
		c <= 0;
	end
	
	
	initial begin
		$dumpfile("out.vcd");
		$dumpvars(0, census_tb);
// 		$monitor(clk);
		
		#400;
		$finish;
	end
	
endmodule

out.vcd
$date
	Thu Mar 31 23:22:16 2016
$end
$version
	Icarus Verilog
$end
$timescale
	1s
$end
$scope module census_tb $end
$var wire 32 ! r [31:0] $end
$var wire 1 " clk $end
$var reg 32 # a [31:0] $end
$var reg 32 $ c [31:0] $end
$var reg 1 % clk_en $end
$var reg 32 & cnt [31:0] $end
$var reg 4 ' op [3:0] $end
$var reg 1 ( reset $end
$scope module comp0 $end
$var wire 32 ) iA [31:0] $end
$var wire 1 " iClk $end
$var wire 1 % iClk_en $end
$var wire 4 * iOp [3:0] $end
$var wire 1 ( iReset $end
$var wire 32 + oRes [31:0] $end
$var wire 120 , wH [119:0] $end
$var wire 7 - wSum [6:0] $end
$var wire 120 . wCodec [119:0] $end
$var reg 32 / rAcc [31:0] $end
$var reg 8 0 rCmp [7:0] $end
$var reg 32 1 rCnt [31:0] $end
$var reg 120 2 rCodec0 [119:0] $end
$var reg 1 3 rDone $end
$var reg 968 4 rMatrix [967:0] $end
$var reg 32 5 rRes [31:0] $end
$scope begin codec_high[61] $end
$upscope $end
$scope begin codec_high[62] $end
$upscope $end
$scope begin codec_high[63] $end
$upscope $end
$scope begin codec_high[64] $end
$upscope $end
$scope begin codec_high[65] $end
$upscope $end
$scope begin codec_high[66] $end
$upscope $end
$scope begin codec_high[67] $end
$upscope $end
$scope begin codec_high[68] $end
$upscope $end
$scope begin codec_high[69] $end
$upscope $end
$scope begin codec_high[70] $end
$upscope $end
$scope begin codec_high[71] $end
$upscope $end
$scope begin codec_high[72] $end
$upscope $end
$scope begin codec_high[73] $end
$upscope $end
$scope begin codec_high[74] $end
$upscope $end
$scope begin codec_high[75] $end
$upscope $end
$scope begin codec_high[76] $end
$upscope $end
$scope begin codec_high[77] $end
$upscope $end
$scope begin codec_high[78] $end
$upscope $end
$scope begin codec_high[79] $end
$upscope $end
$scope begin codec_high[80] $end
$upscope $end
$scope begin codec_high[81] $end
$upscope $end
$scope begin codec_high[82] $end
$upscope $end
$scope begin codec_high[83] $end
$upscope $end
$scope begin codec_high[84] $end
$upscope $end
$scope begin codec_high[85] $end
$upscope $end
$scope begin codec_high[86] $end
$upscope $end
$scope begin codec_high[87] $end
$upscope $end
$scope begin codec_high[88] $end
$upscope $end
$scope begin codec_high[89] $end
$upscope $end
$scope begin codec_high[90] $end
$upscope $end
$scope begin codec_high[91] $end
$upscope $end
$scope begin codec_high[92] $end
$upscope $end
$scope begin codec_high[93] $end
$upscope $end
$scope begin codec_high[94] $end
$upscope $end
$scope begin codec_high[95] $end
$upscope $end
$scope begin codec_high[96] $end
$upscope $end
$scope begin codec_high[97] $end
$upscope $end
$scope begin codec_high[98] $end
$upscope $end
$scope begin codec_high[99] $end
$upscope $end
$scope begin codec_high[100] $end
$upscope $end
$scope begin codec_high[101] $end
$upscope $end
$scope begin codec_high[102] $end
$upscope $end
$scope begin codec_high[103] $end
$upscope $end
$scope begin codec_high[104] $end
$upscope $end
$scope begin codec_high[105] $end
$upscope $end
$scope begin codec_high[106] $end
$upscope $end
$scope begin codec_high[107] $end
$upscope $end
$scope begin codec_high[108] $end
$upscope $end
$scope begin codec_high[109] $end
$upscope $end
$scope begin codec_high[110] $end
$upscope $end
$scope begin codec_high[111] $end
$upscope $end
$scope begin codec_high[112] $end
$upscope $end
$scope begin codec_high[113] $end
$upscope $end
$scope begin codec_high[114] $end
$upscope $end
$scope begin codec_high[115] $end
$upscope $end
$scope begin codec_high[116] $end
$upscope $end
$scope begin codec_high[117] $end
$upscope $end
$scope begin codec_high[118] $end
$upscope $end
$scope begin codec_high[119] $end
$upscope $end
$scope begin codec_high[120] $end
$upscope $end
$scope begin codec_low[0] $end
$upscope $end
$scope begin codec_low[1] $end
$upscope $end
$scope begin codec_low[2] $end
$upscope $end
$scope begin codec_low[3] $end
$upscope $end
$scope begin codec_low[4] $end
$upscope $end
$scope begin codec_low[5] $end
$upscope $end
$scope begin codec_low[6] $end
$upscope $end
$scope begin codec_low[7] $end
$upscope $end
$scope begin codec_low[8] $end
$upscope $end
$scope begin codec_low[9] $end
$upscope $end
$scope begin codec_low[10] $end
$upscope $end
$scope begin codec_low[11] $end
$upscope $end
$scope begin codec_low[12] $end
$upscope $end
$scope begin codec_low[13] $end
$upscope $end
$scope begin codec_low[14] $end
$upscope $end
$scope begin codec_low[15] $end
$upscope $end
$scope begin codec_low[16] $end
$upscope $end
$scope begin codec_low[17] $end
$upscope $end
$scope begin codec_low[18] $end
$upscope $end
$scope begin codec_low[19] $end
$upscope $end
$scope begin codec_low[20] $end
$upscope $end
$scope begin codec_low[21] $end
$upscope $end
$scope begin codec_low[22] $end
$upscope $end
$scope begin codec_low[23] $end
$upscope $end
$scope begin codec_low[24] $end
$upscope $end
$scope begin codec_low[25] $end
$upscope $end
$scope begin codec_low[26] $end
$upscope $end
$scope begin codec_low[27] $end
$upscope $end
$scope begin codec_low[28] $end
$upscope $end
$scope begin codec_low[29] $end
$upscope $end
$scope begin codec_low[30] $end
$upscope $end
$scope begin codec_low[31] $end
$upscope $end
$scope begin codec_low[32] $end
$upscope $end
$scope begin codec_low[33] $end
$upscope $end
$scope begin codec_low[34] $end
$upscope $end
$scope begin codec_low[35] $end
$upscope $end
$scope begin codec_low[36] $end
$upscope $end
$scope begin codec_low[37] $end
$upscope $end
$scope begin codec_low[38] $end
$upscope $end
$scope begin codec_low[39] $end
$upscope $end
$scope begin codec_low[40] $end
$upscope $end
$scope begin codec_low[41] $end
$upscope $end
$scope begin codec_low[42] $end
$upscope $end
$scope begin codec_low[43] $end
$upscope $end
$scope begin codec_low[44] $end
$upscope $end
$scope begin codec_low[45] $end
$upscope $end
$scope begin codec_low[46] $end
$upscope $end
$scope begin codec_low[47] $end
$upscope $end
$scope begin codec_low[48] $end
$upscope $end
$scope begin codec_low[49] $end
$upscope $end
$scope begin codec_low[50] $end
$upscope $end
$scope begin codec_low[51] $end
$upscope $end
$scope begin codec_low[52] $end
$upscope $end
$scope begin codec_low[53] $end
$upscope $end
$scope begin codec_low[54] $end
$upscope $end
$scope begin codec_low[55] $end
$upscope $end
$scope begin codec_low[56] $end
$upscope $end
$scope begin codec_low[57] $end
$upscope $end
$scope begin codec_low[58] $end
$upscope $end
$scope begin codec_low[59] $end
$upscope $end
$upscope $end
$upscope $end
$enddefinitions $end
#0
$dumpvars
bx 5
bx 4
03
bx 2
b0 1
bx 0
b0 /
bx .
bx -
bx ,
bx +
b0 *
bx )
1(
b0 '
b0 &
0%
bx $
bx #
0"
bx !
$end
#1
1"
b1 &
#2
0"
b10 &
0(
#3
1"
b11 &
#4
0"
b100 &
1%
#5
b1 1
13
1"
b101 &
#6
b0 !
b0 +
b0 5
0"
b110 &
#7
1"
b111 &
#8
03
0"
b1000 &
0%
#9
1"
b1001 &
#10
0"
b1010 &
b0 $
b110 #
b110 )
b1 '
b1 *
#11
1"
b1011 &
#12
0"
b1100 &
1%
#13
bx111111111111111111111111111111111111111111111111 4
b10 1
13
1"
b1101 &
#14
0"
b1110 &
#15
1"
b1111 &
#16
03
0"
b10000 &
0%
#17
1"
b10001 &
#18
0"
b10010 &
#19
1"
b10011 &
#20
0"
b10100 &
1%
#21
bx111111111111111111111111111111111111111111111111111111111111111111111111111111111111111111111111 4
b11 1
13
1"
b10101 &
#22
0"
b10110 &
#23
1"
b10111 &
#24
03
0"
b11000 &
0%
#25
1"
b11001 &
#26
0"
b11010 &
#27
1"
b11011 &
#28
0"
b11100 &
1%
#29
bx111111111111111111111111111111111111111111111111111111111111111111111111111111111111111111111111111111111111111111111111111111111111111111111111 4
b100 1
13
1"
b11101 &
#30
0"
b11110 &
#31
1"
b11111 &
#32
03
0"
b100000 &
0%
#33
1"
b100001 &
#34
0"
b100010 &
#35
1"
b100011 &
#36
0"
b100100 &
1%
#37
bx111111111111111111111111111111111111111111111111111111111111111111111111111111111111111111111111111111111111111111111111111111111111111111111111111111111111111111111111111111111111111111111111 4
b101 1
13
1"
b100101 &
#38
0"
b100110 &
#39
1"
b100111 &
#40
03
0"
b101000 &
0%
#41
1"
b101001 &
#42
0"
b101010 &
#43
1"
b101011 &
#44
0"
b101100 &
1%
#45
bx111111111111111111111111111111111111111111111111111111111111111111111111111111111111111111111111111111111111111111111111111111111111111111111111111111111111111111111111111111111111111111111111111111111111111111111111111111111111111111111111 4
b110 1
13
1"
b101101 &
#46
0"
b101110 &
#47
1"
b101111 &
#48
03
0"
b110000 &
0%
#49
1"
b110001 &
#50
0"
b110010 &
#51
1"
b110011 &
#52
0"
b110100 &
1%
#53
bx111111111111111111111111111111111111111111111111111111111111111111111111111111111111111111111111111111111111111111111111111111111111111111111111111111111111111111111111111111111111111111111111111111111111111111111111111111111111111111111111111111111111111111111111111111111111111111111111 4
b111 1
13
1"
b110101 &
#54
0"
b110110 &
#55
1"
b110111 &
#56
03
0"
b111000 &
0%
#57
1"
b111001 &
#58
0"
b111010 &
#59
1"
b111011 &
#60
0"
b111100 &
1%
#61
bx111111111111111111111111111111111111111111111111111111111111111111111111111111111111111111111111111111111111111111111111111111111111111111111111111111111111111111111111111111111111111111111111111111111111111111111111111111111111111111111111111111111111111111111111111111111111111111111111111111111111111111111111111111111111111111111111 4
b1000 1
13
1"
b111101 &
#62
0"
b111110 &
#63
1"
b111111 &
#64
03
0"
b1000000 &
0%
#65
1"
b1000001 &
#66
0"
b1000010 &
#67
1"
b1000011 &
#68
0"
b1000100 &
1%
#69
bx111111111111111111111111111111111111111111111111111111111111111111111111111111111111111111111111111111111111111111111111111111111111111111111111111111111111111111111111111111111111111111111111111111111111111111111111111111111111111111111111111111111111111111111111111111111111111111111111111111111111111111111111111111111111111111111111111111111111111111111111111111111111111111111111 4
b1001 1
13
1"
b1000101 &
#70
0"
b1000110 &
#71
1"
b1000111 &
#72
03
0"
b1001000 &
0%
#73
1"
b1001001 &
#74
0"
b1001010 &
#75
1"
b1001011 &
#76
0"
b1001100 &
1%
#77
bx111111111111111111111111111111111111111111111111111111111111111111111111111111111111111111111111111111111111111111111111111111111111111111111111111111111111111111111111111111111111111111111111111111111111111111111111111111111111111111111111111111111111111111111111111111111111111111111111111111111111111111111111111111111111111111111111111111111111111111111111111111111111111111111111111111111111111111111111111111111111111111111111 4
b1010 1
13
1"
b1001101 &
#78
0"
b1001110 &
#79
1"
b1001111 &
#80
03
0"
b1010000 &
0%
#81
1"
b1010001 &
#82
0"
b1010010 &
#83
1"
b1010011 &
#84
0"
b1010100 &
1%
#85
bx111111111111111111111111111111111111111111111111111111111111111111111111111111111111111111111111111111111111111111111111111111111111111111111111111111111111111111111111111111111111111111111111111111111111111111111111111111111111111111111111111111111111111111111111111111111111111111111111111111111111111111111111111111111111111111111111111111111111111111111111111111111111111111111111111111111111111111111111111111111111111111111111111111111111111111111111111111111111111111111111 4
b1011 1
13
1"
b1010101 &
#86
0"
b1010110 &
#87
1"
b1010111 &
#88
03
0"
b1011000 &
0%
#89
1"
b1011001 &
#90
0"
b1011010 &
#91
1"
b1011011 &
#92
0"
b1011100 &
1%
#93
bx111111111111111111111111111111111111111111111111111111111111111111111111111111111111111111111111111111111111111111111111111111111111111111111111111111111111111111111111111111111111111111111111111111111111111111111111111111111111111111111111111111111111111111111111111111111111111111111111111111111111111111111111111111111111111111111111111111111111111111111111111111111111111111111111111111111111111111111111111111111111111111111111111111111111111111111111111111111111111111111111111111111111111111111111111111111111111111111111 4
b1100 1
13
1"
b1011101 &
#94
0"
b1011110 &
#95
1"
b1011111 &
#96
03
0"
b1100000 &
0%
#97
1"
b1100001 &
#98
0"
b1100010 &
#99
1"
b1100011 &
#100
0"
b1100100 &
1%
#101
bx111111111111111111111111111111111111111111111111111111111111111111111111111111111111111111111111111111111111111111111111111111111111111111111111111111111111111111111111111111111111111111111111111111111111111111111111111111111111111111111111111111111111111111111111111111111111111111111111111111111111111111111111111111111111111111111111111111111111111111111111111111111111111111111111111111111111111111111111111111111111111111111111111111111111111111111111111111111111111111111111111111111111111111111111111111111111111111111111111111111111111111111111111111111111111111111111 4
b1101 1
13
1"
b1100101 &
#102
0"
b1100110 &
#103
1"
b1100111 &
#104
03
0"
b1101000 &
0%
#105
1"
b1101001 &
#106
0"
b1101010 &
#107
1"
b1101011 &
#108
0"
b1101100 &
1%
#109
bx111111111111111111111111111111111111111111111111111111111111111111111111111111111111111111111111111111111111111111111111111111111111111111111111111111111111111111111111111111111111111111111111111111111111111111111111111111111111111111111111111111111111111111111111111111111111111111111111111111111111111111111111111111111111111111111111111111111111111111111111111111111111111111111111111111111111111111111111111111111111111111111111111111111111111111111111111111111111111111111111111111111111111111111111111111111111111111111111111111111111111111111111111111111111111111111111111111111111111111111111111111111111111111111111 4
b1110 1
13
1"
b1101101 &
#110
0"
b1101110 &
#111
1"
b1101111 &
#112
03
0"
b1110000 &
0%
#113
1"
b1110001 &
#114
0"
b1110010 &
#115
1"
b1110011 &
#116
0"
b1110100 &
1%
#117
bx111111111111111111111111111111111111111111111111111111111111111111111111111111111111111111111111111111111111111111111111111111111111111111111111111111111111111111111111111111111111111111111111111111111111111111111111111111111111111111111111111111111111111111111111111111111111111111111111111111111111111111111111111111111111111111111111111111111111111111111111111111111111111111111111111111111111111111111111111111111111111111111111111111111111111111111111111111111111111111111111111111111111111111111111111111111111111111111111111111111111111111111111111111111111111111111111111111111111111111111111111111111111111111111111111111111111111111111111111111111111111111111111 4
b1111 1
13
1"
b1110101 &
#118
0"
b1110110 &
#119
1"
b1110111 &
#120
03
0"
b1111000 &
0%
#121
1"
b1111001 &
#122
0"
b1111010 &
#123
1"
b1111011 &
#124
0"
b1111100 &
1%
#125
bx111111111111111111111111111111111111111111111111111111111111111111111111111111111111111111111111111111111111111111111111111111111111111111111111111111111111111111111111111111111111111111111111111111111111111111111111111111111111111111111111111111111111111111111111111111111111111111111111111111111111111111111111111111111111111111111111111111111111111111111111111111111111111111111111111111111111111111111111111111111111111111111111111111111111111111111111111111111111111111111111111111111111111111111111111111111111111111111111111111111111111111111111111111111111111111111111111111111111111111111111111111111111111111111111111111111111111111111111111111111111111111111111111111111111111111111111111111111111111111111111 4
b10000 1
13
1"
b1111101 &
#126
0"
b1111110 &
#127
1"
b1111111 &
#128
03
0"
b10000000 &
0%
#129
1"
b10000001 &
#130
0"
b10000010 &
#131
1"
b10000011 &
#132
0"
b10000100 &
1%
#133
bx111111111111111111111111111111111111111111111111111111111111111111111111111111111111111111111111111111111111111111111111111111111111111111111111111111111111111111111111111111111111111111111111111111111111111111111111111111111111111111111111111111111111111111111111111111111111111111111111111111111111111111111111111111111111111111111111111111111111111111111111111111111111111111111111111111111111111111111111111111111111111111111111111111111111111111111111111111111111111111111111111111111111111111111111111111111111111111111111111111111111111111111111111111111111111111111111111111111111111111111111111111111111111111111111111111111111111111111111111111111111111111111111111111111111111111111111111111111111111111111111111111111111111111111111111111111111111111111111 4
b10001 1
13
1"
b10000101 &
#134
0"
b10000110 &
#135
1"
b10000111 &
#136
03
0"
b10001000 &
0%
#137
1"
b10001001 &
#138
0"
b10001010 &
#139
1"
b10001011 &
#140
0"
b10001100 &
1%
b10 '
b10 *
#141
bx11111111111111111111111111111111111111111111111111111111111111111111111111111111111111111111111111111111111111111111111111111111111111111111111111111111111111111111111111111111111111111111111111111111111111111111111111111111111111111111111111111111111111111111111111111111111111111111111111111111111111111111111111111111111111111111111111111111111111111111111111111111111111111111111111111111111111111111111111111111111111111111111111111111111111111111111111111111111111111111111111111111111111111111111111111111111111111111111111111111111111111111111111111111111111111111111111111111111111111111111111111111111111111111111111111111111111111111111111111111111111111111111111111111111111111111111111111111111111111111111111111111111111111111111111111111111111111111111100000110 4
b10010 1
13
1"
b10001101 &
#142
0"
b10001110 &
#143
1"
b10001111 &
#144
03
0"
b10010000 &
0%
#145
1"
b10010001 &
#146
0"
b10010010 &
#147
1"
b10010011 &
#148
0"
b10010100 &
1%
#149
bx1111111111111111111111111111111111111111111111111111111111111111111111111111111111111111111111111111111111111111111111111111111111111111111111111111111111111111111111111111111111111111111111111111111111111111111111111111111111111111111111111111111111111111111111111111111111111111111111111111111111111111111111111111111111111111111111111111111111111111111111111111111111111111111111111111111111111111111111111111111111111111111111111111111111111111111111111111111111111111111111111111111111111111111111111111111111111111111111111111111111111111111111111111111111111111111111111111111111111111111111111111111111111111111111111111111111111111111111111111111111111111111111111111111111111111111111111111111111111111111111111111111111111111111111111111111111111111111111110000011000000110 4
b10011 1
13
1"
b10010101 &
#150
0"
b10010110 &
#151
1"
b10010111 &
#152
03
0"
b10011000 &
0%
#153
1"
b10011001 &
#154
0"
b10011010 &
#155
1"
b10011011 &
#156
0"
b10011100 &
1%
#157
bx111111111111111111111111111111111111111111111111111111111111111111111111111111111111111111111111111111111111111111111111111111111111111111111111111111111111111111111111111111111111111111111111111111111111111111111111111111111111111111111111111111111111111111111111111111111111111111111111111111111111111111111111111111111111111111111111111111111111111111111111111111111111111111111111111111111111111111111111111111111111111111111111111111111111111111111111111111111111111111111111111111111111111111111111111111111111111111111111111111111111111111111111111111111111111111111111111111111111111111111111111111111111111111111111111111111111111111111111111111111111111111111111111111111111111111111111111111111111111111111111111111111111111111111111111111111111111111111111000001100000011000000110 4
b10100 1
13
1"
b10011101 &
#158
0"
b10011110 &
#159
1"
b10011111 &
#160
03
0"
b10100000 &
0%
#161
1"
b10100001 &
#162
0"
b10100010 &
#163
1"
b10100011 &
#164
0"
b10100100 &
1%
#165
bx11111111111111111111111111111111111111111111111111111111111111111111111111111111111111111111111111111111111111111111111111111111111111111111111111111111111111111111111111111111111111111111111111111111111111111111111111111111111111111111111111111111111111111111111111111111111111111111111111111111111111111111111111111111111111111111111111111111111111111111111111111111111111111111111111111111111111111111111111111111111111111111111111111111111111111111111111111111111111111111111111111111111111111111111111111111111111111111111111111111111111111111111111111111111111111111111111111111111111111111111111111111111111111111111111111111111111111111111111111111111111111111111111111111111111111111111111111111111111111111111111111111111111111111111111111111111111111111111100000110000001100000011000000110 4
b10101 1
13
1"
b10100101 &
#166
0"
b10100110 &
#167
1"
b10100111 &
#168
03
0"
b10101000 &
0%
#169
1"
b10101001 &
#170
0"
b10101010 &
#171
1"
b10101011 &
#172
0"
b10101100 &
1%
#173
bx1111111111111111111111111111111111111111111111111111111111111111111111111111111111111111111111111111111111111111111111111111111111111111111111111111111111111111111111111111111111111111111111111111111111111111111111111111111111111111111111111111111111111111111111111111111111111111111111111111111111111111111111111111111111111111111111111111111111111111111111111111111111111111111111111111111111111111111111111111111111111111111111111111111111111111111111111111111111111111111111111111111111111111111111111111111111111111111111111111111111111111111111111111111111111111111111111111111111111111111111111111111111111111111111111111111111111111111111111111111111111111111111111111111111111111111111111111111111111111111111111111111111111111111111111111111111111111111111110000011000000110000001100000011000000110 4
b10110 1
13
1"
b10101101 &
#174
0"
b10101110 &
#175
1"
b10101111 &
#176
03
0"
b10110000 &
0%
#177
1"
b10110001 &
#178
0"
b10110010 &
#179
1"
b10110011 &
#180
0"
b10110100 &
1%
#181
bx111111111111111111111111111111111111111111111111111111111111111111111111111111111111111111111111111111111111111111111111111111111111111111111111111111111111111111111111111111111111111111111111111111111111111111111111111111111111111111111111111111111111111111111111111111111111111111111111111111111111111111111111111111111111111111111111111111111111111111111111111111111111111111111111111111111111111111111111111111111111111111111111111111111111111111111111111111111111111111111111111111111111111111111111111111111111111111111111111111111111111111111111111111111111111111111111111111111111111111111111111111111111111111111111111111111111111111111111111111111111111111111111111111111111111111111111111111111111111111111111111111111111111111111111111111111111111111111111000001100000011000000110000001100000011000000110 4
b10111 1
13
1"
b10110101 &
#182
0"
b10110110 &
#183
1"
b10110111 &
#184
03
0"
b10111000 &
0%
#185
1"
b10111001 &
#186
0"
b10111010 &
b1 '
b1 *
#187
1"
b10111011 &
#188
0"
b10111100 &
1%
#189
bx111111111111111111111111111111111111111111111111111111111111111111111111111111111111111111111111111111111111111111111111111111111111111111111111111111111111111111111111111111111111111111111111111111111111111111111111111111111111111111111111111111111111111111111111111111111111111111111111111111111111111111111111111111111111111111111111111111111111111111111111111111111111111111111111111111111111111111111111111111111111111111111111111111111111111111111111111111111111111111111111111111111111111111111111111111111111111111111111111111111111111111111111111111111111111111111111111111111111111111111111111111111111111111111111111111111111111111111111111111111111111111111111111111111111111111111111111111111111111111111111111111111111111111111111111111111111111111111111000001100000011000000110000001100000011000000110111111111111111111111111111111111111111111111111 4
b11000 1
13
1"
b10111101 &
#190
0"
b10111110 &
#191
1"
b10111111 &
#192
03
0"
b11000000 &
0%
#193
1"
b11000001 &
#194
0"
b11000010 &
#195
1"
b11000011 &
#196
0"
b11000100 &
1%
#197
bx111111111111111111111111111111111111111111111111111111111111111111111111111111111111111111111111111111111111111111111111111111111111111111111111111111111111111111111111111111111111111111111111111111111111111111111111111111111111111111111111111111111111111111111111111111111111111111111111111111111111111111111111111111111111111111111111111111111111111111111111111111111111111111111111111111111111111111111111111111111111111111111111111111111111111111111111111111111111111111111111111111111111111111111111111111111111111111111111111111111111111111111111111111111111111111111111111111111111111111111111111111111111111111111111111111111111111111111111111111111111111111111111111111111111111111111111111111111111111111111111111111111111111111111111111111111111111111111111000001100000011000000110000001100000011000000110111111111111111111111111111111111111111111111111111111111111111111111111111111111111111111111111 4
b11001 1
13
1"
b11000101 &
#198
0"
b11000110 &
#199
1"
b11000111 &
#200
03
0"
b11001000 &
0%
#201
1"
b11001001 &
#202
0"
b11001010 &
#203
1"
b11001011 &
#204
0"
b11001100 &
1%
#205
bx111111111111111111111111111111111111111111111111111111111111111111111111111111111111111111111111111111111111111111111111111111111111111111111111111111111111111111111111111111111111111111111111111111111111111111111111111111111111111111111111111111111111111111111111111111111111111111111111111111111111111111111111111111111111111111111111111111111111111111111111111111111111111111111111111111111111111111111111111111111111111111111111111111111111111111111111111111111111111111111111111111111111111111111111111111111111111111111111111111111111111111111111111111111111111111111111111111111111111111111111111111111111111111111111111111111111111111111111111111111111111111111111111111111111111111111111111111111111111111111111111111111111111111111111111111111111111111111111000001100000011000000110000001100000011000000110111111111111111111111111111111111111111111111111111111111111111111111111111111111111111111111111111111111111111111111111111111111111111111111111 4
b11010 1
13
1"
b11001101 &
#206
0"
b11001110 &
#207
1"
b11001111 &
#208
03
0"
b11010000 &
0%
#209
1"
b11010001 &
#210
0"
b11010010 &
#211
1"
b11010011 &
#212
0"
b11010100 &
1%
#213
b11111111111111111111111111111111111111111111111111111111111111111111111111111111111111111111111111111111111111111111111111111111111111111111111111111111111111111111111111111111111111111111111111111111111111111111111111111111111111111111111111111111111111111111111111111111111111111111111111111111111111111111111111111111111111111111111111111111111111111111111111111111111111111111111111111111111111111111111111111111111111111111111111111111111111111111111111111111111111111111111111111111111111111111111111111111111111111111111111111111111111111111111111111111111111111111111111111111111111111111111111111111111111111111111111111111111111111111111111111111111111111111111111111111111111111111111111111111111111111111111111111111000001100000011000000110000001100000011000000110111111111111111111111111111111111111111111111111111111111111111111111111111111111111111111111111111111111111111111111111111111111111111111111111111111111111111111111111111111111111111111111111 4
b11011 1
13
1"
b11010101 &
#214
0"
b11010110 &
#215
1"
b11010111 &
#216
03
0"
b11011000 &
0%
#217
1"
b11011001 &
#218
0"
b11011010 &
#219
1"
b11011011 &
#220
0"
b11011100 &
1%
b1010 #
b1010 )
#221
b11111111111111111111111111111111111111111111111111111111111111111111111111111111111111111111111111111111111111111111111111111111111111111111111111111111111111111111111111111111111111111111111111111111111111111111111111111111111111111111111111111111111111111111111111111111111111111111111111111111111111111111111111111111111111111111111111111111111111111111111111111111111111111111111111111111111111111111111111111111111111111111111111111111111111111111111111111111111111111111111111111111111111111111111111111111111111111111111111111111111111111111111111111111111111111111111111111111111111111111111111111111111111111111111111111111111111111111111111111111111111111111111111111111111111111111111111111111111111110000011000000110000001100000011000000110000001101111111111111111111111111111111111111111111111111111111111111111111111111111111111111111111111111111111111111111111111111111111111111111111111111111111111111111111111111111111111111111111111111111111111111111 4
b11100 1
13
1"
b11011101 &
#222
0"
b11011110 &
